RegisterFile.v
module RegisterFile(
  input clk,
  input reset,    // Active-low reset signal
  input [4:0] addrA,
  input [4:0] addrB,
  input [4:0] addrD,
  input [31:0] dataD,
  input reg_write,
  output reg [31:0] dataA,
  output reg [31:0] dataB
);
    reg [31:0] registers [31:0]; // Register file: 32 general-purpose registers, each 32 bits wide

    integer i;

    always @(posedge clk or negedge reset) begin
        if (reset == 1'b0) begin
            for (i = 0; i < 32; i = i + 1)
                registers[i] <= 32'b0;
        end else if (reg_write == 1'b1) begin
            registers[addrD] <= dataD;
        end
    end

    always @(*) begin
        if (reset == 1'b0) begin
            dataA = 32'b0;
            dataB = 32'b0;
        end else begin
            dataA = registers[addrA];
            dataB = registers[addrB];
        end
    end
endmodule

wave.vcd
$version Generated by VerilatedVcd $end
$timescale 1ps $end
 $scope module TOP $end
  $var wire 1 D clk $end
  $var wire 1 E reset $end
  $var wire 5 F addrA [4:0] $end
  $var wire 5 G addrB [4:0] $end
  $var wire 5 H addrD [4:0] $end
  $var wire 32 I dataD [31:0] $end
  $var wire 1 J reg_write $end
  $var wire 32 K dataA [31:0] $end
  $var wire 32 L dataB [31:0] $end
  $scope module RegisterFile $end
   $var wire 1 D clk $end
   $var wire 1 E reset $end
   $var wire 5 F addrA [4:0] $end
   $var wire 5 G addrB [4:0] $end
   $var wire 5 H addrD [4:0] $end
   $var wire 32 I dataD [31:0] $end
   $var wire 1 J reg_write $end
   $var wire 32 K dataA [31:0] $end
   $var wire 32 L dataB [31:0] $end
   $var wire 32 # registers[0] [31:0] $end
   $var wire 32 $ registers[1] [31:0] $end
   $var wire 32 % registers[2] [31:0] $end
   $var wire 32 & registers[3] [31:0] $end
   $var wire 32 ' registers[4] [31:0] $end
   $var wire 32 ( registers[5] [31:0] $end
   $var wire 32 ) registers[6] [31:0] $end
   $var wire 32 * registers[7] [31:0] $end
   $var wire 32 + registers[8] [31:0] $end
   $var wire 32 , registers[9] [31:0] $end
   $var wire 32 - registers[10] [31:0] $end
   $var wire 32 . registers[11] [31:0] $end
   $var wire 32 / registers[12] [31:0] $end
   $var wire 32 0 registers[13] [31:0] $end
   $var wire 32 1 registers[14] [31:0] $end
   $var wire 32 2 registers[15] [31:0] $end
   $var wire 32 3 registers[16] [31:0] $end
   $var wire 32 4 registers[17] [31:0] $end
   $var wire 32 5 registers[18] [31:0] $end
   $var wire 32 6 registers[19] [31:0] $end
   $var wire 32 7 registers[20] [31:0] $end
   $var wire 32 8 registers[21] [31:0] $end
   $var wire 32 9 registers[22] [31:0] $end
   $var wire 32 : registers[23] [31:0] $end
   $var wire 32 ; registers[24] [31:0] $end
   $var wire 32 < registers[25] [31:0] $end
   $var wire 32 = registers[26] [31:0] $end
   $var wire 32 > registers[27] [31:0] $end
   $var wire 32 ? registers[28] [31:0] $end
   $var wire 32 @ registers[29] [31:0] $end
   $var wire 32 A registers[30] [31:0] $end
   $var wire 32 B registers[31] [31:0] $end
   $var wire 32 C i [31:0] $end
  $upscope $end
 $upscope $end
$enddefinitions $end


#0
b00000000000000000000000000000000 #
b00000000000000000000000000000000 $
b00000000000000000000000000000000 %
b00000000000000000000000000000000 &
b00000000000000000000000000000000 '
b00000000000000000000000000000000 (
b00000000000000000000000000000000 )
b00000000000000000000000000000000 *
b00000000000000000000000000000000 +
b00000000000000000000000000000000 ,
b00000000000000000000000000000000 -
b00000000000000000000000000000000 .
b00000000000000000000000000000000 /
b00000000000000000000000000000000 0
b00000000000000000000000000000000 1
b00000000000000000000000000000000 2
b00000000000000000000000000000000 3
b00000000000000000000000000000000 4
b00000000000000000000000000000000 5
b00000000000000000000000000000000 6
b00000000000000000000000000000000 7
b00000000000000000000000000000000 8
b00000000000000000000000000000000 9
b00000000000000000000000000000000 :
b00000000000000000000000000000000 ;
b00000000000000000000000000000000 <
b00000000000000000000000000000000 =
b00000000000000000000000000000000 >
b00000000000000000000000000000000 ?
b00000000000000000000000000000000 @
b00000000000000000000000000000000 A
b00000000000000000000000000000000 B
b00000000000000000000000000000000 C
0D
0E
b00000 F
b00000 G
b00000 H
b00000000000000000000000000000000 I
0J
b00000000000000000000000000000000 K
b00000000000000000000000000000000 L
#1
b00000000000000000000000000100000 C
1D
#2
0D
#3
1D
#4
0D
1E
b00101 H
b00010010001101000101011001111000 I
1J
#5
b00010010001101000101011001111000 (
1D
#6
0D
b01010 H
b10000111011001010100001100100001 I
#7
b10000111011001010100001100100001 -
1D
#8
0D
b01111 H
b10100101101001011010010110100101 I
#9
b10100101101001011010010110100101 2
1D
#10
0D
b11111 H
b11111111111111111111111111111111 I
#11
b11111111111111111111111111111111 B
1D
#12
0D
0J
#13
1D
#14
0D
b00101 F
b01010 G
b00010010001101000101011001111000 K
b10000111011001010100001100100001 L
#15
1D
#16
0D
b01111 F
b11111 G
b10100101101001011010010110100101 K
b11111111111111111111111111111111 L
#17
1D
#18
b00000000000000000000000000000000 (
b00000000000000000000000000000000 -
b00000000000000000000000000000000 2
b00000000000000000000000000000000 B
0D
0E
b00000000000000000000000000000000 K
b00000000000000000000000000000000 L
#19
1D
#20
0D
1E
#21
1D
#22
0D
b00101 F
b01010 G
b00000 H
b11011110101011011011111011101111 I
1J
#23
b11011110101011011011111011101111 #
1D
