RegisterFile.v
module RegisterFile(
  input clk,
  input reset,    // Active-low reset signal
  input [4:0] addrA,
  input [4:0] addrB,
  input [4:0] addrD,
  input [31:0] dataD,
  input reg_write,
  output reg [31:0] dataA,
  output reg [31:0] dataB
);
    reg [31:0] registers [31:0]; // Register file: 32 general-purpose registers, each 32 bits wide

    integer i;

    always @(posedge clk or negedge reset) begin
        if (reset == 1'b0) begin
            for (i = 0; i < 32; i = i + 1)
                registers[i] <= 32'b0;
        end else if (reg_write == 1'b1) begin
            registers[addrD] <= dataD;
        end
    end

    always @(*) begin
        if (reset == 1'b0) begin
            dataA = 32'b0;
            dataB = 32'b0;
        end else begin
            dataA = registers[addrA];
            dataB = registers[addrB];
        end
    end
endmodule

wave.vcd
$version Generated by VerilatedVcd $end
$timescale 1ps $end
 $scope module TOP $end
  $var wire 1 D clk $end
  $var wire 1 E reset $end
  $var wire 5 F addrA [4:0] $end
  $var wire 5 G addrB [4:0] $end
  $var wire 5 H addrD [4:0] $end
  $var wire 32 I dataD [31:0] $end
  $var wire 1 J reg_write $end
  $var wire 32 K dataA [31:0] $end
  $var wire 32 L dataB [31:0] $end
  $scope module RegisterFile $end
   $var wire 1 D clk $end
   $var wire 1 E reset $end
   $var wire 5 F addrA [4:0] $end
   $var wire 5 G addrB [4:0] $end
   $var wire 5 H addrD [4:0] $end
   $var wire 32 I dataD [31:0] $end
   $var wire 1 J reg_write $end
   $var wire 32 K dataA [31:0] $end
   $var wire 32 L dataB [31:0] $end
   $var wire 32 # registers[0] [31:0] $end
   $var wire 32 $ registers[1] [31:0] $end
   $var wire 32 % registers[2] [31:0] $end
   $var wire 32 & registers[3] [31:0] $end
   $var wire 32 ' registers[4] [31:0] $end
   $var wire 32 ( registers[5] [31:0] $end
   $var wire 32 ) registers[6] [31:0] $end
   $var wire 32 * registers[7] [31:0] $end
   $var wire 32 + registers[8] [31:0] $end
   $var wire 32 , registers[9] [31:0] $end
   $var wire 32 - registers[10] [31:0] $end
   $var wire 32 . registers[11] [31:0] $end
   $var wire 32 / registers[12] [31:0] $end
   $var wire 32 0 registers[13] [31:0] $end
   $var wire 32 1 registers[14] [31:0] $end
   $var wire 32 2 registers[15] [31:0] $end
   $var wire 32 3 registers[16] [31:0] $end
   $var wire 32 4 registers[17] [31:0] $end
   $var wire 32 5 registers[18] [31:0] $end
   $var wire 32 6 registers[19] [31:0] $end
   $var wire 32 7 registers[20] [31:0] $end
   $var wire 32 8 registers[21] [31:0] $end
   $var wire 32 9 registers[22] [31:0] $end
   $var wire 32 : registers[23] [31:0] $end
   $var wire 32 ; registers[24] [31:0] $end
   $var wire 32 < registers[25] [31:0] $end
   $var wire 32 = registers[26] [31:0] $end
   $var wire 32 > registers[27] [31:0] $end
   $var wire 32 ? registers[28] [31:0] $end
   $var wire 32 @ registers[29] [31:0] $end
   $var wire 32 A registers[30] [31:0] $end
   $var wire 32 B registers[31] [31:0] $end
   $var wire 32 C i [31:0] $end
  $upscope $end
 $upscope $end
$enddefinitions $end


#0
b00000000000000000000000000000000 #
b00000000000000000000000000000000 $
b00000000000000000000000000000000 %
b00000000000000000000000000000000 &
b00000000000000000000000000000000 '
b00000000000000000000000000000000 (
b00000000000000000000000000000000 )
b00000000000000000000000000000000 *
b00000000000000000000000000000000 +
b00000000000000000000000000000000 ,
b00000000000000000000000000000000 -
b00000000000000000000000000000000 .
b00000000000000000000000000000000 /
b00000000000000000000000000000000 0
b00000000000000000000000000000000 1
b00000000000000000000000000000000 2
b00000000000000000000000000000000 3
b00000000000000000000000000000000 4
b00000000000000000000000000000000 5
b00000000000000000000000000000000 6
b00000000000000000000000000000000 7
b00000000000000000000000000000000 8
b00000000000000000000000000000000 9
b00000000000000000000000000000000 :
b00000000000000000000000000000000 ;
b00000000000000000000000000000000 <
b00000000000000000000000000000000 =
b00000000000000000000000000000000 >
b00000000000000000000000000000000 ?
b00000000000000000000000000000000 @
b00000000000000000000000000000000 A
b00000000000000000000000000000000 B
b00000000000000000000000000000000 C
1D
0E
b00000 F
b00000 G
b00000 H
b00000000000000000000000000000000 I
0J
b00000000000000000000000000000000 K
b00000000000000000000000000000000 L
#1
0D
#2
b00000000000000000000000000100000 C
1D
#3
0D
#4
b00010001000100010001000100010010 $
1D
1E
b00001 H
b00010001000100010001000100010010 I
1J
#5
0D
#6
b00010001000100010001000100010011 %
1D
b00010 H
b00010001000100010001000100010011 I
#7
0D
#8
b00010001000100010001000100010100 &
1D
b00011 H
b00010001000100010001000100010100 I
#9
0D
#10
b00010001000100010001000100010101 '
1D
b00100 H
b00010001000100010001000100010101 I
#11
0D
#12
b00010001000100010001000100010110 (
1D
b00101 H
b00010001000100010001000100010110 I
#13
0D
#14
b00010001000100010001000100010111 )
1D
b00110 H
b00010001000100010001000100010111 I
#15
0D
#16
b00010001000100010001000100011000 *
1D
b00111 H
b00010001000100010001000100011000 I
#17
0D
#18
b00010001000100010001000100011001 +
1D
b01000 H
b00010001000100010001000100011001 I
#19
0D
#20
b00010001000100010001000100011010 ,
1D
b01001 H
b00010001000100010001000100011010 I
#21
0D
#22
b00010001000100010001000100011011 -
1D
b01010 H
b00010001000100010001000100011011 I
#23
0D
#24
b00010001000100010001000100011100 .
1D
b01011 H
b00010001000100010001000100011100 I
#25
0D
#26
b00010001000100010001000100011101 /
1D
b01100 H
b00010001000100010001000100011101 I
#27
0D
#28
b00010001000100010001000100011110 0
1D
b01101 H
b00010001000100010001000100011110 I
#29
0D
#30
b00010001000100010001000100011111 1
1D
b01110 H
b00010001000100010001000100011111 I
#31
0D
#32
b00010001000100010001000100100000 2
1D
b01111 H
b00010001000100010001000100100000 I
#33
0D
#34
b00010001000100010001000100100001 3
1D
b10000 H
b00010001000100010001000100100001 I
#35
0D
#36
b00010001000100010001000100100010 4
1D
b10001 H
b00010001000100010001000100100010 I
#37
0D
#38
b00010001000100010001000100100011 5
1D
b10010 H
b00010001000100010001000100100011 I
#39
0D
#40
b00010001000100010001000100100100 6
1D
b10011 H
b00010001000100010001000100100100 I
#41
0D
#42
b00010001000100010001000100100101 7
1D
b10100 H
b00010001000100010001000100100101 I
#43
0D
#44
b00010001000100010001000100100110 8
1D
b10101 H
b00010001000100010001000100100110 I
#45
0D
#46
b00010001000100010001000100100111 9
1D
b10110 H
b00010001000100010001000100100111 I
#47
0D
#48
b00010001000100010001000100101000 :
1D
b10111 H
b00010001000100010001000100101000 I
#49
0D
#50
b00010001000100010001000100101001 ;
1D
b11000 H
b00010001000100010001000100101001 I
#51
0D
#52
b00010001000100010001000100101010 <
1D
b11001 H
b00010001000100010001000100101010 I
#53
0D
#54
b00010001000100010001000100101011 =
1D
b11010 H
b00010001000100010001000100101011 I
#55
0D
#56
b00010001000100010001000100101100 >
1D
b11011 H
b00010001000100010001000100101100 I
#57
0D
#58
b00010001000100010001000100101101 ?
1D
b11100 H
b00010001000100010001000100101101 I
#59
0D
#60
b00010001000100010001000100101110 @
1D
b11101 H
b00010001000100010001000100101110 I
#61
0D
#62
b00010001000100010001000100101111 A
1D
b11110 H
b00010001000100010001000100101111 I
#63
0D
#64
b00010001000100010001000100110000 B
1D
b11111 H
b00010001000100010001000100110000 I
#65
0D
#66
1D
0J
#67
0D
#68
1D
b00001 F
b00010 G
b00010001000100010001000100010010 K
b00010001000100010001000100010011 L
#69
0D
#70
1D
b00010 F
b00011 G
b00010001000100010001000100010011 K
b00010001000100010001000100010100 L
#71
0D
#72
1D
b00011 F
b00100 G
b00010001000100010001000100010100 K
b00010001000100010001000100010101 L
#73
0D
#74
1D
b00100 F
b00101 G
b00010001000100010001000100010101 K
b00010001000100010001000100010110 L
#75
0D
#76
1D
b00101 F
b00110 G
b00010001000100010001000100010110 K
b00010001000100010001000100010111 L
#77
0D
#78
1D
b00110 F
b00111 G
b00010001000100010001000100010111 K
b00010001000100010001000100011000 L
#79
0D
#80
1D
b00111 F
b01000 G
b00010001000100010001000100011000 K
b00010001000100010001000100011001 L
#81
0D
#82
1D
b01000 F
b01001 G
b00010001000100010001000100011001 K
b00010001000100010001000100011010 L
#83
0D
#84
1D
b01001 F
b01010 G
b00010001000100010001000100011010 K
b00010001000100010001000100011011 L
#85
0D
#86
1D
b01010 F
b01011 G
b00010001000100010001000100011011 K
b00010001000100010001000100011100 L
#87
0D
#88
1D
b01011 F
b01100 G
b00010001000100010001000100011100 K
b00010001000100010001000100011101 L
#89
0D
#90
1D
b01100 F
b01101 G
b00010001000100010001000100011101 K
b00010001000100010001000100011110 L
#91
0D
#92
1D
b01101 F
b01110 G
b00010001000100010001000100011110 K
b00010001000100010001000100011111 L
#93
0D
#94
1D
b01110 F
b01111 G
b00010001000100010001000100011111 K
b00010001000100010001000100100000 L
#95
0D
#96
1D
b01111 F
b10000 G
b00010001000100010001000100100000 K
b00010001000100010001000100100001 L
#97
0D
#98
1D
b10000 F
b10001 G
b00010001000100010001000100100001 K
b00010001000100010001000100100010 L
#99
0D
#100
1D
b10001 F
b10010 G
b00010001000100010001000100100010 K
b00010001000100010001000100100011 L
#101
0D
#102
1D
b10010 F
b10011 G
b00010001000100010001000100100011 K
b00010001000100010001000100100100 L
#103
0D
#104
1D
b10011 F
b10100 G
b00010001000100010001000100100100 K
b00010001000100010001000100100101 L
#105
0D
#106
1D
b10100 F
b10101 G
b00010001000100010001000100100101 K
b00010001000100010001000100100110 L
#107
0D
#108
1D
b10101 F
b10110 G
b00010001000100010001000100100110 K
b00010001000100010001000100100111 L
#109
0D
#110
1D
b10110 F
b10111 G
b00010001000100010001000100100111 K
b00010001000100010001000100101000 L
#111
0D
#112
1D
b10111 F
b11000 G
b00010001000100010001000100101000 K
b00010001000100010001000100101001 L
#113
0D
#114
1D
b11000 F
b11001 G
b00010001000100010001000100101001 K
b00010001000100010001000100101010 L
#115
0D
#116
1D
b11001 F
b11010 G
b00010001000100010001000100101010 K
b00010001000100010001000100101011 L
#117
0D
#118
1D
b11010 F
b11011 G
b00010001000100010001000100101011 K
b00010001000100010001000100101100 L
#119
0D
#120
1D
b11011 F
b11100 G
b00010001000100010001000100101100 K
b00010001000100010001000100101101 L
#121
0D
#122
1D
b11100 F
b11101 G
b00010001000100010001000100101101 K
b00010001000100010001000100101110 L
#123
0D
#124
1D
b11101 F
b11110 G
b00010001000100010001000100101110 K
b00010001000100010001000100101111 L
#125
0D
#126
1D
b11110 F
b11111 G
b00010001000100010001000100101111 K
b00010001000100010001000100110000 L
#127
0D
#128
1D
b11111 F
b00000 G
b00010001000100010001000100110000 K
b00000000000000000000000000000000 L
#129
0D
#130
1D
#131
0D
#132
b00000000000000000000000000000000 $
b00000000000000000000000000000000 %
b00000000000000000000000000000000 &
b00000000000000000000000000000000 '
b00000000000000000000000000000000 (
b00000000000000000000000000000000 )
b00000000000000000000000000000000 *
b00000000000000000000000000000000 +
b00000000000000000000000000000000 ,
b00000000000000000000000000000000 -
b00000000000000000000000000000000 .
b00000000000000000000000000000000 /
b00000000000000000000000000000000 0
b00000000000000000000000000000000 1
b00000000000000000000000000000000 2
b00000000000000000000000000000000 3
b00000000000000000000000000000000 4
b00000000000000000000000000000000 5
b00000000000000000000000000000000 6
b00000000000000000000000000000000 7
b00000000000000000000000000000000 8
b00000000000000000000000000000000 9
b00000000000000000000000000000000 :
b00000000000000000000000000000000 ;
b00000000000000000000000000000000 <
b00000000000000000000000000000000 =
b00000000000000000000000000000000 >
b00000000000000000000000000000000 ?
b00000000000000000000000000000000 @
b00000000000000000000000000000000 A
b00000000000000000000000000000000 B
1D
0E
b00000000000000000000000000000000 K
#133
0D
#134
1D
1E
#135
0D
#136
1D
b00101 F
b01010 G
#137
0D
#138
1D
b00000 H
b11011110101011011011111011101111 I
1J
#139
0D
#140
1D
0J
#141
0D
#142
1D
b00000 F
b00000 G
