RegisterFile.v
module RegisterFile(
  input clk,
  input reset,    // Active-low reset signal
  input [4:0] addrA,
  input [4:0] addrB,
  input [4:0] addrD,
  input [31:0] dataD,
  input reg_write,
  output reg [31:0] dataA,
  output reg [31:0] dataB
);
    reg [31:0] registers [31:0]; // Register file: 32 general-purpose registers, each 32 bits wide

    integer i;

    always @(posedge clk or negedge reset) begin
        if (reset == 1'b0) begin
            for (i = 0; i < 32; i = i + 1)
                registers[i] <= 32'b0;
        end else if (reg_write == 1'b1) begin
            registers[addrD] <= dataD;
        end
    end

    always @(*) begin
        if (reset == 1'b0) begin
            dataA = 32'b0;
            dataB = 32'b0;
        end else begin
            dataA = registers[addrA];
            dataB = registers[addrB];
        end
    end
endmodule

Pipeline_Processor/test/tb_RegisterFile.v
`timescale 1ns/1ps
// `include "../rtl/RegisterFile.v"


module tb_RegisterFile;

    // DUT signals
    reg clk = 1;
    reg reset = 1;
    reg reg_write = 0;
    reg [4:0] addrA = 0, addrB = 0, addrD = 0;
    reg [31:0] dataD = 0;
    wire [31:0] dataA, dataB;

    // Instantiate the DUT
    RegisterFile dut (
        .clk(clk),
        .reset(reset),
        .reg_write(reg_write),
        .addrA(addrA),
        .addrB(addrB),
        .addrD(addrD),
        .dataD(dataD),
        .dataA(dataA),
        .dataB(dataB)
    );

    // Clock generation
    always #5 clk = ~clk;

    // Task to write to a register
    task write_reg(input [4:0] addr, input [31:0] val);
    begin
        addrD = addr;
        dataD = val;
        reg_write = 1;
        @(posedge clk);
        reg_write = 0;
    end
    endtask

    // Task to read from two registers
    task read_regs(input [4:0] addr1, input [4:0] addr2, output [31:0] out1, output [31:0] out2);
    begin
        addrA = addr1;
        addrB = addr2;
        #1; // small delay for combinational logic to settle
        out1 = dataA;
        out2 = dataB;
    end
    endtask

    integer i;
    reg [31:0] outA, outB;

    initial begin
        $dumpfile("obj/RegisterFile/wave.vcd");
        $dumpvars(0, tb_RegisterFile);

        $display("Applying reset...");
        reset = 0;
        @(posedge clk); @(posedge clk);
        reset = 1;
        @(posedge clk);

        $display("Testing register writes...");
        for (i = 1; i < 32; i = i + 1) begin
            write_reg(i, 32'h11111111 + i);
        end

        @(posedge clk);

        $display("Verifying reads...");
        for (i = 1; i < 32; i = i + 1) begin
            read_regs(i, ((i + 1) % 32), outA, outB);
            $display("R%0d: 0x%08x (expected 0x%08x)", i, outA, 32'h11111111 + i);
            if (outA !== (32'h11111111 + i)) begin
                $display("❌ Test failed at R%0d", i);
                $finish;
            end
            @(posedge clk);
        end

        $display("Re-applying reset...");
        reset = 0;
        @(posedge clk);
        reset = 1;
        @(posedge clk);

        read_regs(5, 10, outA, outB);
        $display("After reset - R5: 0x%08x, R10: 0x%08x", outA, outB);
        if (outA !== 32'h0 || outB !== 32'h0) begin
            $display("❌ Reset failed!");
            $finish;
        end

        $display("Performing edge cases test (write to R0)...");
        write_reg(0, 32'hDEADBEEF);
        @(posedge clk);
        read_regs(0, 0, outA, outB);
        @(posedge clk);
        $display("R0: 0x%08x (expected 0x00000000)", outA);
        if (outA !== 32'h0) begin
            $display("❌ R0 write protection failed!");
            $finish;
        end

        $display("\n✅ All tests passed successfully.");
        $finish;
    end

endmodule
// RegisterFile module for reference

Pipeline_Processor/obj/RegisterFile/wave.vcd
$date
	Thu Apr 17 02:28:57 2025
$end
$version
	Icarus Verilog
$end
$timescale
	1ps
$end
$scope module tb_RegisterFile $end
$var wire 32 ! dataB [31:0] $end
$var wire 32 " dataA [31:0] $end
$var reg 5 # addrA [4:0] $end
$var reg 5 $ addrB [4:0] $end
$var reg 5 % addrD [4:0] $end
$var reg 1 & clk $end
$var reg 32 ' dataD [31:0] $end
$var reg 32 ( outA [31:0] $end
$var reg 32 ) outB [31:0] $end
$var reg 1 * reg_write $end
$var reg 1 + reset $end
$var integer 32 , i [31:0] $end
$scope module dut $end
$var wire 5 - addrA [4:0] $end
$var wire 5 . addrB [4:0] $end
$var wire 5 / addrD [4:0] $end
$var wire 1 & clk $end
$var wire 32 0 dataD [31:0] $end
$var wire 1 * reg_write $end
$var wire 1 + reset $end
$var reg 32 1 dataA [31:0] $end
$var reg 32 2 dataB [31:0] $end
$var integer 32 3 i [31:0] $end
$upscope $end
$scope task read_regs $end
$var reg 5 4 addr1 [4:0] $end
$var reg 5 5 addr2 [4:0] $end
$var reg 32 6 out1 [31:0] $end
$var reg 32 7 out2 [31:0] $end
$upscope $end
$scope task write_reg $end
$var reg 5 8 addr [4:0] $end
$var reg 32 9 val [31:0] $end
$upscope $end
$upscope $end
$enddefinitions $end
#0
$dumpvars
bx 9
bx 8
bx 7
bx 6
bx 5
bx 4
b100000 3
b0 2
b0 1
b0 0
b0 /
b0 .
b0 -
bx ,
0+
0*
bx )
bx (
b0 '
1&
b0 %
b0 $
b0 #
b0 "
b0 !
$end
#5000
0&
#10000
b100000 3
1&
#15000
0&
#20000
1+
1&
#25000
0&
#30000
1*
b10001000100010001000100010010 '
b10001000100010001000100010010 0
b1 %
b1 /
b10001000100010001000100010010 9
b1 8
b1 ,
1&
#35000
0&
#40000
b10001000100010001000100010011 '
b10001000100010001000100010011 0
b10 %
b10 /
b10001000100010001000100010011 9
b10 8
b10 ,
1*
1&
#45000
0&
#50000
b10001000100010001000100010100 '
b10001000100010001000100010100 0
b11 %
b11 /
b10001000100010001000100010100 9
b11 8
b11 ,
1*
1&
#55000
0&
#60000
b10001000100010001000100010101 '
b10001000100010001000100010101 0
b100 %
b100 /
b10001000100010001000100010101 9
b100 8
b100 ,
1*
1&
#65000
0&
#70000
b10001000100010001000100010110 '
b10001000100010001000100010110 0
b101 %
b101 /
b10001000100010001000100010110 9
b101 8
b101 ,
1*
1&
#75000
0&
#80000
b10001000100010001000100010111 '
b10001000100010001000100010111 0
b110 %
b110 /
b10001000100010001000100010111 9
b110 8
b110 ,
1*
1&
#85000
0&
#90000
b10001000100010001000100011000 '
b10001000100010001000100011000 0
b111 %
b111 /
b10001000100010001000100011000 9
b111 8
b111 ,
1*
1&
#95000
0&
#100000
b10001000100010001000100011001 '
b10001000100010001000100011001 0
b1000 %
b1000 /
b10001000100010001000100011001 9
b1000 8
b1000 ,
1*
1&
#105000
0&
#110000
b10001000100010001000100011010 '
b10001000100010001000100011010 0
b1001 %
b1001 /
b10001000100010001000100011010 9
b1001 8
b1001 ,
1*
1&
#115000
0&
#120000
b10001000100010001000100011011 '
b10001000100010001000100011011 0
b1010 %
b1010 /
b10001000100010001000100011011 9
b1010 8
b1010 ,
1*
1&
#125000
0&
#130000
b10001000100010001000100011100 '
b10001000100010001000100011100 0
b1011 %
b1011 /
b10001000100010001000100011100 9
b1011 8
b1011 ,
1*
1&
#135000
0&
#140000
b10001000100010001000100011101 '
b10001000100010001000100011101 0
b1100 %
b1100 /
b10001000100010001000100011101 9
b1100 8
b1100 ,
1*
1&
#145000
0&
#150000
b10001000100010001000100011110 '
b10001000100010001000100011110 0
b1101 %
b1101 /
b10001000100010001000100011110 9
b1101 8
b1101 ,
1*
1&
#155000
0&
#160000
b10001000100010001000100011111 '
b10001000100010001000100011111 0
b1110 %
b1110 /
b10001000100010001000100011111 9
b1110 8
b1110 ,
1*
1&
#165000
0&
#170000
b10001000100010001000100100000 '
b10001000100010001000100100000 0
b1111 %
b1111 /
b10001000100010001000100100000 9
b1111 8
b1111 ,
1*
1&
#175000
0&
#180000
b10001000100010001000100100001 '
b10001000100010001000100100001 0
b10000 %
b10000 /
b10001000100010001000100100001 9
b10000 8
b10000 ,
1*
1&
#185000
0&
#190000
b10001000100010001000100100010 '
b10001000100010001000100100010 0
b10001 %
b10001 /
b10001000100010001000100100010 9
b10001 8
b10001 ,
1*
1&
#195000
0&
#200000
b10001000100010001000100100011 '
b10001000100010001000100100011 0
b10010 %
b10010 /
b10001000100010001000100100011 9
b10010 8
b10010 ,
1*
1&
#205000
0&
#210000
b10001000100010001000100100100 '
b10001000100010001000100100100 0
b10011 %
b10011 /
b10001000100010001000100100100 9
b10011 8
b10011 ,
1*
1&
#215000
0&
#220000
b10001000100010001000100100101 '
b10001000100010001000100100101 0
b10100 %
b10100 /
b10001000100010001000100100101 9
b10100 8
b10100 ,
1*
1&
#225000
0&
#230000
b10001000100010001000100100110 '
b10001000100010001000100100110 0
b10101 %
b10101 /
b10001000100010001000100100110 9
b10101 8
b10101 ,
1*
1&
#235000
0&
#240000
b10001000100010001000100100111 '
b10001000100010001000100100111 0
b10110 %
b10110 /
b10001000100010001000100100111 9
b10110 8
b10110 ,
1*
1&
#245000
0&
#250000
b10001000100010001000100101000 '
b10001000100010001000100101000 0
b10111 %
b10111 /
b10001000100010001000100101000 9
b10111 8
b10111 ,
1*
1&
#255000
0&
#260000
b10001000100010001000100101001 '
b10001000100010001000100101001 0
b11000 %
b11000 /
b10001000100010001000100101001 9
b11000 8
b11000 ,
1*
1&
#265000
0&
#270000
b10001000100010001000100101010 '
b10001000100010001000100101010 0
b11001 %
b11001 /
b10001000100010001000100101010 9
b11001 8
b11001 ,
1*
1&
#275000
0&
#280000
b10001000100010001000100101011 '
b10001000100010001000100101011 0
b11010 %
b11010 /
b10001000100010001000100101011 9
b11010 8
b11010 ,
1*
1&
#285000
0&
#290000
b10001000100010001000100101100 '
b10001000100010001000100101100 0
b11011 %
b11011 /
b10001000100010001000100101100 9
b11011 8
b11011 ,
1*
1&
#295000
0&
#300000
b10001000100010001000100101101 '
b10001000100010001000100101101 0
b11100 %
b11100 /
b10001000100010001000100101101 9
b11100 8
b11100 ,
1*
1&
#305000
0&
#310000
b10001000100010001000100101110 '
b10001000100010001000100101110 0
b11101 %
b11101 /
b10001000100010001000100101110 9
b11101 8
b11101 ,
1*
1&
#315000
0&
#320000
b10001000100010001000100101111 '
b10001000100010001000100101111 0
b11110 %
b11110 /
b10001000100010001000100101111 9
b11110 8
b11110 ,
1*
1&
#325000
0&
#330000
b10001000100010001000100110000 '
b10001000100010001000100110000 0
b11111 %
b11111 /
b10001000100010001000100110000 9
b11111 8
b11111 ,
1*
1&
#335000
0&
#340000
b100000 ,
0*
1&
#345000
0&
#350000
b10001000100010001000100010011 !
b10001000100010001000100010011 2
b10001000100010001000100010010 "
b10001000100010001000100010010 1
b10 $
b10 .
b1 #
b1 -
b10 5
b1 4
b1 ,
1&
#351000
b10001000100010001000100010011 )
b10001000100010001000100010010 (
b10001000100010001000100010011 7
b10001000100010001000100010010 6
#355000
0&
#360000
b10001000100010001000100010100 !
b10001000100010001000100010100 2
b10001000100010001000100010011 "
b10001000100010001000100010011 1
b11 $
b11 .
b10 #
b10 -
b11 5
b10 4
b10 ,
1&
#361000
b10001000100010001000100010100 )
b10001000100010001000100010011 (
b10001000100010001000100010100 7
b10001000100010001000100010011 6
#365000
0&
#370000
b10001000100010001000100010101 !
b10001000100010001000100010101 2
b10001000100010001000100010100 "
b10001000100010001000100010100 1
b100 $
b100 .
b11 #
b11 -
b100 5
b11 4
b11 ,
1&
#371000
b10001000100010001000100010101 )
b10001000100010001000100010100 (
b10001000100010001000100010101 7
b10001000100010001000100010100 6
#375000
0&
#380000
b10001000100010001000100010110 !
b10001000100010001000100010110 2
b10001000100010001000100010101 "
b10001000100010001000100010101 1
b101 $
b101 .
b100 #
b100 -
b101 5
b100 4
b100 ,
1&
#381000
b10001000100010001000100010110 )
b10001000100010001000100010101 (
b10001000100010001000100010110 7
b10001000100010001000100010101 6
#385000
0&
#390000
b10001000100010001000100010111 !
b10001000100010001000100010111 2
b10001000100010001000100010110 "
b10001000100010001000100010110 1
b110 $
b110 .
b101 #
b101 -
b110 5
b101 4
b101 ,
1&
#391000
b10001000100010001000100010111 )
b10001000100010001000100010110 (
b10001000100010001000100010111 7
b10001000100010001000100010110 6
#395000
0&
#400000
b10001000100010001000100011000 !
b10001000100010001000100011000 2
b10001000100010001000100010111 "
b10001000100010001000100010111 1
b111 $
b111 .
b110 #
b110 -
b111 5
b110 4
b110 ,
1&
#401000
b10001000100010001000100011000 )
b10001000100010001000100010111 (
b10001000100010001000100011000 7
b10001000100010001000100010111 6
#405000
0&
#410000
b10001000100010001000100011001 !
b10001000100010001000100011001 2
b10001000100010001000100011000 "
b10001000100010001000100011000 1
b1000 $
b1000 .
b111 #
b111 -
b1000 5
b111 4
b111 ,
1&
#411000
b10001000100010001000100011001 )
b10001000100010001000100011000 (
b10001000100010001000100011001 7
b10001000100010001000100011000 6
#415000
0&
#420000
b10001000100010001000100011010 !
b10001000100010001000100011010 2
b10001000100010001000100011001 "
b10001000100010001000100011001 1
b1001 $
b1001 .
b1000 #
b1000 -
b1001 5
b1000 4
b1000 ,
1&
#421000
b10001000100010001000100011010 )
b10001000100010001000100011001 (
b10001000100010001000100011010 7
b10001000100010001000100011001 6
#425000
0&
#430000
b10001000100010001000100011011 !
b10001000100010001000100011011 2
b10001000100010001000100011010 "
b10001000100010001000100011010 1
b1010 $
b1010 .
b1001 #
b1001 -
b1010 5
b1001 4
b1001 ,
1&
#431000
b10001000100010001000100011011 )
b10001000100010001000100011010 (
b10001000100010001000100011011 7
b10001000100010001000100011010 6
#435000
0&
#440000
b10001000100010001000100011100 !
b10001000100010001000100011100 2
b10001000100010001000100011011 "
b10001000100010001000100011011 1
b1011 $
b1011 .
b1010 #
b1010 -
b1011 5
b1010 4
b1010 ,
1&
#441000
b10001000100010001000100011100 )
b10001000100010001000100011011 (
b10001000100010001000100011100 7
b10001000100010001000100011011 6
#445000
0&
#450000
b10001000100010001000100011101 !
b10001000100010001000100011101 2
b10001000100010001000100011100 "
b10001000100010001000100011100 1
b1100 $
b1100 .
b1011 #
b1011 -
b1100 5
b1011 4
b1011 ,
1&
#451000
b10001000100010001000100011101 )
b10001000100010001000100011100 (
b10001000100010001000100011101 7
b10001000100010001000100011100 6
#455000
0&
#460000
b10001000100010001000100011110 !
b10001000100010001000100011110 2
b10001000100010001000100011101 "
b10001000100010001000100011101 1
b1101 $
b1101 .
b1100 #
b1100 -
b1101 5
b1100 4
b1100 ,
1&
#461000
b10001000100010001000100011110 )
b10001000100010001000100011101 (
b10001000100010001000100011110 7
b10001000100010001000100011101 6
#465000
0&
#470000
b10001000100010001000100011111 !
b10001000100010001000100011111 2
b10001000100010001000100011110 "
b10001000100010001000100011110 1
b1110 $
b1110 .
b1101 #
b1101 -
b1110 5
b1101 4
b1101 ,
1&
#471000
b10001000100010001000100011111 )
b10001000100010001000100011110 (
b10001000100010001000100011111 7
b10001000100010001000100011110 6
#475000
0&
#480000
b10001000100010001000100100000 !
b10001000100010001000100100000 2
b10001000100010001000100011111 "
b10001000100010001000100011111 1
b1111 $
b1111 .
b1110 #
b1110 -
b1111 5
b1110 4
b1110 ,
1&
#481000
b10001000100010001000100100000 )
b10001000100010001000100011111 (
b10001000100010001000100100000 7
b10001000100010001000100011111 6
#485000
0&
#490000
b10001000100010001000100100001 !
b10001000100010001000100100001 2
b10001000100010001000100100000 "
b10001000100010001000100100000 1
b10000 $
b10000 .
b1111 #
b1111 -
b10000 5
b1111 4
b1111 ,
1&
#491000
b10001000100010001000100100001 )
b10001000100010001000100100000 (
b10001000100010001000100100001 7
b10001000100010001000100100000 6
#495000
0&
#500000
b10001000100010001000100100010 !
b10001000100010001000100100010 2
b10001000100010001000100100001 "
b10001000100010001000100100001 1
b10001 $
b10001 .
b10000 #
b10000 -
b10001 5
b10000 4
b10000 ,
1&
#501000
b10001000100010001000100100010 )
b10001000100010001000100100001 (
b10001000100010001000100100010 7
b10001000100010001000100100001 6
#505000
0&
#510000
b10001000100010001000100100011 !
b10001000100010001000100100011 2
b10001000100010001000100100010 "
b10001000100010001000100100010 1
b10010 $
b10010 .
b10001 #
b10001 -
b10010 5
b10001 4
b10001 ,
1&
#511000
b10001000100010001000100100011 )
b10001000100010001000100100010 (
b10001000100010001000100100011 7
b10001000100010001000100100010 6
#515000
0&
#520000
b10001000100010001000100100100 !
b10001000100010001000100100100 2
b10001000100010001000100100011 "
b10001000100010001000100100011 1
b10011 $
b10011 .
b10010 #
b10010 -
b10011 5
b10010 4
b10010 ,
1&
#521000
b10001000100010001000100100100 )
b10001000100010001000100100011 (
b10001000100010001000100100100 7
b10001000100010001000100100011 6
#525000
0&
#530000
b10001000100010001000100100101 !
b10001000100010001000100100101 2
b10001000100010001000100100100 "
b10001000100010001000100100100 1
b10100 $
b10100 .
b10011 #
b10011 -
b10100 5
b10011 4
b10011 ,
1&
#531000
b10001000100010001000100100101 )
b10001000100010001000100100100 (
b10001000100010001000100100101 7
b10001000100010001000100100100 6
#535000
0&
#540000
b10001000100010001000100100110 !
b10001000100010001000100100110 2
b10001000100010001000100100101 "
b10001000100010001000100100101 1
b10101 $
b10101 .
b10100 #
b10100 -
b10101 5
b10100 4
b10100 ,
1&
#541000
b10001000100010001000100100110 )
b10001000100010001000100100101 (
b10001000100010001000100100110 7
b10001000100010001000100100101 6
#545000
0&
#550000
b10001000100010001000100100111 !
b10001000100010001000100100111 2
b10001000100010001000100100110 "
b10001000100010001000100100110 1
b10110 $
b10110 .
b10101 #
b10101 -
b10110 5
b10101 4
b10101 ,
1&
#551000
b10001000100010001000100100111 )
b10001000100010001000100100110 (
b10001000100010001000100100111 7
b10001000100010001000100100110 6
#555000
0&
#560000
b10001000100010001000100101000 !
b10001000100010001000100101000 2
b10001000100010001000100100111 "
b10001000100010001000100100111 1
b10111 $
b10111 .
b10110 #
b10110 -
b10111 5
b10110 4
b10110 ,
1&
#561000
b10001000100010001000100101000 )
b10001000100010001000100100111 (
b10001000100010001000100101000 7
b10001000100010001000100100111 6
#565000
0&
#570000
b10001000100010001000100101001 !
b10001000100010001000100101001 2
b10001000100010001000100101000 "
b10001000100010001000100101000 1
b11000 $
b11000 .
b10111 #
b10111 -
b11000 5
b10111 4
b10111 ,
1&
#571000
b10001000100010001000100101001 )
b10001000100010001000100101000 (
b10001000100010001000100101001 7
b10001000100010001000100101000 6
#575000
0&
#580000
b10001000100010001000100101010 !
b10001000100010001000100101010 2
b10001000100010001000100101001 "
b10001000100010001000100101001 1
b11001 $
b11001 .
b11000 #
b11000 -
b11001 5
b11000 4
b11000 ,
1&
#581000
b10001000100010001000100101010 )
b10001000100010001000100101001 (
b10001000100010001000100101010 7
b10001000100010001000100101001 6
#585000
0&
#590000
b10001000100010001000100101011 !
b10001000100010001000100101011 2
b10001000100010001000100101010 "
b10001000100010001000100101010 1
b11010 $
b11010 .
b11001 #
b11001 -
b11010 5
b11001 4
b11001 ,
1&
#591000
b10001000100010001000100101011 )
b10001000100010001000100101010 (
b10001000100010001000100101011 7
b10001000100010001000100101010 6
#595000
0&
#600000
b10001000100010001000100101100 !
b10001000100010001000100101100 2
b10001000100010001000100101011 "
b10001000100010001000100101011 1
b11011 $
b11011 .
b11010 #
b11010 -
b11011 5
b11010 4
b11010 ,
1&
#601000
b10001000100010001000100101100 )
b10001000100010001000100101011 (
b10001000100010001000100101100 7
b10001000100010001000100101011 6
#605000
0&
#610000
b10001000100010001000100101101 !
b10001000100010001000100101101 2
b10001000100010001000100101100 "
b10001000100010001000100101100 1
b11100 $
b11100 .
b11011 #
b11011 -
b11100 5
b11011 4
b11011 ,
1&
#611000
b10001000100010001000100101101 )
b10001000100010001000100101100 (
b10001000100010001000100101101 7
b10001000100010001000100101100 6
#615000
0&
#620000
b10001000100010001000100101110 !
b10001000100010001000100101110 2
b10001000100010001000100101101 "
b10001000100010001000100101101 1
b11101 $
b11101 .
b11100 #
b11100 -
b11101 5
b11100 4
b11100 ,
1&
#621000
b10001000100010001000100101110 )
b10001000100010001000100101101 (
b10001000100010001000100101110 7
b10001000100010001000100101101 6
#625000
0&
#630000
b10001000100010001000100101111 !
b10001000100010001000100101111 2
b10001000100010001000100101110 "
b10001000100010001000100101110 1
b11110 $
b11110 .
b11101 #
b11101 -
b11110 5
b11101 4
b11101 ,
1&
#631000
b10001000100010001000100101111 )
b10001000100010001000100101110 (
b10001000100010001000100101111 7
b10001000100010001000100101110 6
#635000
0&
#640000
b10001000100010001000100110000 !
b10001000100010001000100110000 2
b10001000100010001000100101111 "
b10001000100010001000100101111 1
b11111 $
b11111 .
b11110 #
b11110 -
b11111 5
b11110 4
b11110 ,
1&
#641000
b10001000100010001000100110000 )
b10001000100010001000100101111 (
b10001000100010001000100110000 7
b10001000100010001000100101111 6
#645000
0&
#650000
b0 !
b0 2
b10001000100010001000100110000 "
b10001000100010001000100110000 1
b0 $
b0 .
b11111 #
b11111 -
b0 5
b11111 4
b11111 ,
1&
#651000
b0 )
b10001000100010001000100110000 (
b0 7
b10001000100010001000100110000 6
#655000
0&
#660000
b0 "
b0 1
b100000 3
0+
b100000 ,
1&
#665000
0&
#670000
1+
1&
#675000
0&
#680000
b1010 $
b1010 .
b101 #
b101 -
b1010 5
b101 4
1&
#681000
1*
b11011110101011011011111011101111 '
b11011110101011011011111011101111 0
b0 %
b0 /
b11011110101011011011111011101111 9
b0 8
b0 (
b0 6
#685000
0&
#690000
0*
1&
#695000
0&
#700000
b0 $
b0 .
b0 #
b0 -
b0 5
b0 4
1&
